candle_nn-0.4.2.dist-info/METADATA
candle_nn-0.4.2.dist-info/WHEEL
candle/__init__.pyi
candle/__init__.py
candle/testing/__init__.py
candle/models/llama.py
candle/models/bert.py
candle/onnx/__init__.pyi
candle/onnx/__init__.py
candle/typing/__init__.py
candle/nn/normalization.py
candle/nn/container.py
candle/nn/__init__.py
candle/nn/linear.py
candle/nn/sparse.py
candle/nn/module.py
candle/functional/__init__.pyi
candle/functional/__init__.py
candle/utils/__init__.pyi
candle/utils/__init__.py
candle/candle.abi3.so
candle_nn-0.4.2.dist-info/RECORD
