Metadata-Version: 2.1
Name: candle-nn
Version: 0.4.2
Requires-Dist: pytest ; extra == 'testing'
Requires-Dist: black ==22.3 ; extra == 'testing'
Requires-Dist: transformers >=4.33.3 ; extra == 'huggingface'
Requires-Dist: huggingface-hub >=0.17.3 ; extra == 'huggingface'
Provides-Extra: testing
Provides-Extra: huggingface
Summary: Minimalist ML framework.
Keywords: blas,tensor,machine-learning
Author: The Candle Team
License: MIT OR Apache-2.0
Requires-Python: >=3.7
Project-URL: Homepage, https://github.com/huggingface/candle
Project-URL: Source, https://github.com/huggingface/candle
